seeq/base/__init__.py
seeq/base/proputil.py
seeq/base/seeq_names.py
seeq/base/system.py
seeq/base/util.py
seeq/spy/__init__.py
seeq/spy/__init__.sq-variables.py
seeq/spy/_archive.py
seeq/spy/_common.py
seeq/spy/_compatibility.py
seeq/spy/_config.py
seeq/spy/_context.py
seeq/spy/_datalab.py
seeq/spy/_dependencies.py
seeq/spy/_errors.py
seeq/spy/_login.py
seeq/spy/_metadata.py
seeq/spy/_metadata_push_results.py
seeq/spy/_plot.py
seeq/spy/_pull.py
seeq/spy/_push.py
seeq/spy/_redaction.py
seeq/spy/_search.py
seeq/spy/_session.py
seeq/spy/_status.py
seeq/spy/_swap.py
seeq/spy/_upgrade.py
seeq/spy/_url.py
seeq/spy/_usage.py
seeq/spy/acl/__init__.py
seeq/spy/acl/_pull.py
seeq/spy/acl/_push.py
seeq/spy/acl/tests/__init__.py
seeq/spy/acl/tests/test_pull.py
seeq/spy/acl/tests/test_push.py
seeq/spy/addons/__init__.py
seeq/spy/addons/_install.py
seeq/spy/addons/_permissions.py
seeq/spy/addons/_search.py
seeq/spy/addons/_uninstall.py
seeq/spy/addons/tests/test_common.py
seeq/spy/addons/tests/test_install.py
seeq/spy/addons/tests/test_search.py
seeq/spy/addons/tests/test_uninstall.py
seeq/spy/assets/__init__.py
seeq/spy/assets/_brochure.py
seeq/spy/assets/_build.py
seeq/spy/assets/_context.py
seeq/spy/assets/_model.py
seeq/spy/assets/brochure.html
seeq/spy/assets/_trees/__init__.py
seeq/spy/assets/_trees/_constants.py
seeq/spy/assets/_trees/_csv.py
seeq/spy/assets/_trees/_match.py
seeq/spy/assets/_trees/_pandas.py
seeq/spy/assets/_trees/_path.py
seeq/spy/assets/_trees/_properties.py
seeq/spy/assets/_trees/_pull.py
seeq/spy/assets/_trees/_tree.py
seeq/spy/assets/_trees/_utils.py
seeq/spy/assets/_trees/_validate.py
seeq/spy/assets/_trees/tests/__init__.py
seeq/spy/assets/_trees/tests/test_tree_system.py
seeq/spy/assets/_trees/tests/test_tree_unit.py
seeq/spy/assets/tests/__init__.py
seeq/spy/assets/tests/automated_asset_structure.py
seeq/spy/assets/tests/test_assets_system.py
seeq/spy/assets/tests/test_assets_unit.py
seeq/spy/assets/tests/test_crab_32080.py
seeq_spy-197.25.dist-info/METADATA
seeq_spy-197.25.dist-info/WHEEL
seeq_spy-197.25.dist-info/top_level.txt
seeq_spy-197.25.dist-info/RECORD
