Metadata-Version: 2.4
Name: seeq-spy
Version: 197.25
Summary: Easy-to-use Python interface for Seeq
Author-email: Seeq Corporation <support@seeq.com>
License: Seeq Python Library – License File
Project-URL: Homepage, https://www.seeq.com
Project-URL: Documentation, https://python-docs.seeq.com/
Project-URL: Changelog, https://python-docs.seeq.com/changelog.html
Classifier: Programming Language :: Python :: 3
Classifier: License :: Other/Proprietary License
Classifier: Operating System :: OS Independent
Requires-Python: >=3.8
Requires-Dist: Deprecated>=1.2.6
Requires-Dist: numpy>=1.21.6
Requires-Dist: pandas>=1.2.5
Requires-Dist: python-dateutil>=2.7.3
Requires-Dist: pytz>=2020.1
Requires-Dist: requests>=2.22.0
Requires-Dist: urllib3>=1.21.1
Provides-Extra: widgets
Requires-Dist: ipython>=7.6.1; extra == "widgets"
Requires-Dist: ipywidgets>=7.6.0; extra == "widgets"
Requires-Dist: matplotlib>=3.5.0; extra == "widgets"
Requires-Dist: seeq-data-lab-env-mgr>=0.1.0; extra == "widgets"
Provides-Extra: templates
Requires-Dist: beautifulsoup4>=4.8.0; extra == "templates"
Requires-Dist: chevron>=0.14.0; extra == "templates"
Requires-Dist: Mako>=1.1.0; extra == "templates"
Requires-Dist: Markdown>=3.3.4; extra == "templates"
Requires-Dist: matplotlib>=3.5.0; extra == "templates"
Provides-Extra: jobs
Requires-Dist: cron-descriptor>=1.2.24; extra == "jobs"
Requires-Dist: jupyter_client>=7.2.0; extra == "jobs"
Requires-Dist: nbconvert>=6.4.4; extra == "jobs"
Requires-Dist: nbformat>=5.2.0; extra == "jobs"
Requires-Dist: recurrent>=0.4.0; extra == "jobs"
Provides-Extra: jupyter
Requires-Dist: ipylab>=0.5.2; extra == "jupyter"
Requires-Dist: ipython>=7.6.1; extra == "jupyter"
Requires-Dist: ipywidgets>=7.6.0; extra == "jupyter"
Requires-Dist: jupyterlab>=3.0.0; extra == "jupyter"
Requires-Dist: nbconvert>=6.4.4; extra == "jupyter"
Requires-Dist: nbformat>=5.2.0; extra == "jupyter"
Requires-Dist: notebook>=6.0.0; extra == "jupyter"
Requires-Dist: psutil>=5.9.0; extra == "jupyter"
Requires-Dist: setuptools>=65.0.0; extra == "jupyter"
Provides-Extra: all
Requires-Dist: beautifulsoup4>=4.8.0; extra == "all"
Requires-Dist: chevron>=0.14.0; extra == "all"
Requires-Dist: cron-descriptor>=1.2.24; extra == "all"
Requires-Dist: ipylab>=0.5.2; extra == "all"
Requires-Dist: ipywidgets>=7.6.0; extra == "all"
Requires-Dist: jupyterlab>=3.0.0; extra == "all"
Requires-Dist: Markdown>=3.3.4; extra == "all"
Requires-Dist: matplotlib>=3.5.0; extra == "all"
Requires-Dist: nbconvert>=6.4.4; extra == "all"
Requires-Dist: nbformat>=5.2.0; extra == "all"
Requires-Dist: notebook>=6.0.0; extra == "all"
Requires-Dist: psutil>=5.9.0; extra == "all"
Requires-Dist: recurrent>=0.4.0; extra == "all"
Requires-Dist: setuptools>=65.0.0; extra == "all"
Requires-Dist: ipython>=7.6.1; extra == "all"
Requires-Dist: Mako>=1.1.0; extra == "all"
Requires-Dist: seeq-data-lab-env-mgr>=0.1.0; extra == "all"
Requires-Dist: jupyter_client>=7.2.0; extra == "all"
